{
  "_current_date": "2026-09-01",
  "access_groups": {
    "GRP-ENGCORE": {
      "description": "Baseline engineering systems access",
      "eligible_departments": [
        "ENG"
      ],
      "eligible_roles": [],
      "group_code": "GRP-ENGCORE",
      "member_count": 124,
      "name": "Engineering Core Access",
      "requires_approval": false
    },
    "GRP-VPNEMP": {
      "description": "VPN access for employees",
      "eligible_departments": [],
      "eligible_roles": [],
      "group_code": "GRP-VPNEMP",
      "member_count": 876,
      "name": "Corporate VPN Users",
      "requires_approval": false
    }
  },
  "active_outages": {},
  "asset_recoveries": {},
  "assets": {
    "AST-LPT-000101": {
      "asset_tag": "AST-LPT-000101",
      "asset_type": "laptop",
      "assigned_employee_id": "EMP000101",
      "lifecycle_status": "current",
      "manufacturer": "Lenovo",
      "model": "ThinkPad X1 Carbon",
      "os": "windows",
      "purchase_date": "2024-02-01",
      "serial_number": "LNX1000101",
      "size": "14-inch",
      "status": "active",
      "warranty_expiration": "2027-02-01"
    },
    "AST-LPT-310482": {
      "asset_tag": "AST-LPT-310482",
      "asset_type": "laptop",
      "assigned_employee_id": "EMP031482",
      "lifecycle_status": "current",
      "manufacturer": "Dell",
      "model": "Latitude 7440",
      "os": "windows",
      "purchase_date": "2024-01-18",
      "serial_number": "DL7440-310482",
      "size": "14-inch",
      "status": "active",
      "warranty_expiration": "2027-01-18"
    },
    "AST-LPT-729480": {
      "asset_tag": "AST-LPT-729480",
      "asset_type": "laptop",
      "assigned_employee_id": "EMP072948",
      "lifecycle_status": "current",
      "manufacturer": "Apple",
      "model": "MacBook Pro",
      "os": "macos",
      "purchase_date": "2023-03-10",
      "serial_number": "MBP729480",
      "size": "14-inch",
      "status": "active",
      "warranty_expiration": "2026-03-10"
    },
    "AST-MON-000101": {
      "asset_tag": "AST-MON-000101",
      "asset_type": "monitor",
      "assigned_employee_id": "EMP000101",
      "lifecycle_status": "current",
      "manufacturer": "Dell",
      "model": "P2422H",
      "os": null,
      "purchase_date": "2024-02-01",
      "serial_number": "MN000101",
      "size": "24-inch",
      "status": "active",
      "warranty_expiration": "2027-02-01"
    },
    "AST-MON-310483": {
      "asset_tag": "AST-MON-310483",
      "asset_type": "monitor",
      "assigned_employee_id": "EMP031482",
      "lifecycle_status": "current",
      "manufacturer": "Dell",
      "model": "UltraSharp U2722D",
      "os": null,
      "purchase_date": "2024-01-18",
      "serial_number": "MN310483",
      "size": "27-inch",
      "status": "active",
      "warranty_expiration": "2027-01-18"
    },
    "AST-MON-729481": {
      "asset_tag": "AST-MON-729481",
      "asset_type": "monitor",
      "assigned_employee_id": "EMP072948",
      "lifecycle_status": "current",
      "manufacturer": "LG",
      "model": "27UP850",
      "os": null,
      "purchase_date": "2023-03-10",
      "serial_number": "MN729481",
      "size": "27-inch",
      "status": "active",
      "warranty_expiration": "2026-03-10"
    }
  },
  "calendar_events": {},
  "cases": {},
  "cost_centers": {
    "CC-1101": {
      "cost_center_code": "CC-1101",
      "department_code": "ENG",
      "description": "Engineering Delivery",
      "has_budget": true,
      "remaining_budget_usd": 85000
    },
    "CC-1102": {
      "cost_center_code": "CC-1102",
      "department_code": "ENG",
      "description": "Engineering Leadership",
      "has_budget": true,
      "remaining_budget_usd": 125000
    }
  },
  "employees": {
    "EMP000101": {
      "account_status": {
        "active_directory": {
          "lock_reason": null,
          "locked": false,
          "requires_in_person_reset": false
        },
        "email": {
          "lock_reason": null,
          "locked": false,
          "requires_in_person_reset": false
        },
        "erp": {
          "lock_reason": null,
          "locked": false,
          "requires_in_person_reset": false
        },
        "sso": {
          "lock_reason": null,
          "locked": false,
          "requires_in_person_reset": false
        },
        "vpn": {
          "lock_reason": null,
          "locked": false,
          "requires_in_person_reset": false
        }
      },
      "assigned_desk": "BLD3-FL3-D301",
      "assigned_parking": "PZA-001",
      "building_code": "BLD3",
      "cost_center_code": "CC-1102",
      "date_of_birth": "1979-12-03",
      "department_code": "ENG",
      "direct_reports": [
        "EMP031482"
      ],
      "employee_id": "EMP000101",
      "employment_status": "active",
      "ergonomic_assessment": {
        "completed_date": "2025-08-14",
        "status": "completed"
      },
      "first_name": "Marina",
      "floor_code": "FL3",
      "group_memberships": [
        {
          "added_date": "2014-09-15",
          "group_code": "GRP-ENGCORE",
          "group_name": "Engineering Core Access",
          "status": "active"
        }
      ],
      "hardware_entitlements": {
        "laptop_replacement": {
          "current_asset_tag": "AST-LPT-000101",
          "pending_request": false,
          "pending_request_id": null
        },
        "monitor_bundle": {
          "current_asset_tag": "AST-MON-000101",
          "pending_request": false,
          "pending_request_id": null
        }
      },
      "hire_date": "2014-09-15",
      "is_manager": true,
      "last_desk_assignment_date": "2025-12-01",
      "last_name": "Patel",
      "last_parking_assignment_date": "2025-12-01",
      "manager_auth_code": "Z8Q7L1",
      "manager_employee_id": null,
      "offboarding_record": {
        "access_removed": false,
        "initiated_by": null,
        "initiated_date": null,
        "last_working_day": null,
        "removal_case_id": null,
        "removal_scope": null,
        "status": null
      },
      "otp_code": "654120",
      "pending_role_change": {
        "effective_date": null,
        "hr_case_id": null,
        "new_role_code": null
      },
      "phone_last_four": "5502",
      "role_code": "DIRECTOR",
      "software_licenses": []
    },
    "EMP031482": {
      "account_status": {
        "active_directory": {
          "lock_reason": null,
          "locked": false,
          "requires_in_person_reset": false
        },
        "email": {
          "lock_reason": null,
          "locked": false,
          "requires_in_person_reset": false
        },
        "erp": {
          "lock_reason": null,
          "locked": false,
          "requires_in_person_reset": false
        },
        "sso": {
          "lock_reason": null,
          "locked": false,
          "requires_in_person_reset": false
        },
        "vpn": {
          "lock_reason": null,
          "locked": false,
          "requires_in_person_reset": false
        }
      },
      "assigned_desk": "BLD3-FL2-D204",
      "assigned_parking": "PZA-118",
      "building_code": "BLD3",
      "cost_center_code": "CC-1101",
      "date_of_birth": "1987-04-16",
      "department_code": "ENG",
      "direct_reports": [
        "EMP072948"
      ],
      "employee_id": "EMP031482",
      "employment_status": "active",
      "ergonomic_assessment": {
        "completed_date": "2025-11-21",
        "status": "completed"
      },
      "first_name": "Priya",
      "floor_code": "FL2",
      "group_memberships": [
        {
          "added_date": "2018-06-11",
          "group_code": "GRP-ENGCORE",
          "group_name": "Engineering Core Access",
          "status": "active"
        },
        {
          "added_date": "2018-06-11",
          "group_code": "GRP-VPNEMP",
          "group_name": "Corporate VPN Users",
          "status": "active"
        }
      ],
      "hardware_entitlements": {
        "laptop_replacement": {
          "current_asset_tag": "AST-LPT-310482",
          "pending_request": false,
          "pending_request_id": null
        },
        "monitor_bundle": {
          "current_asset_tag": "AST-MON-310483",
          "pending_request": false,
          "pending_request_id": null
        }
      },
      "hire_date": "2018-06-11",
      "is_manager": true,
      "last_desk_assignment_date": "2026-03-15",
      "last_name": "Ramaswamy",
      "last_parking_assignment_date": "2026-01-10",
      "manager_auth_code": "K4M2P9",
      "manager_employee_id": "EMP000101",
      "offboarding_record": {
        "access_removed": false,
        "initiated_by": null,
        "initiated_date": null,
        "last_working_day": null,
        "removal_case_id": null,
        "removal_scope": null,
        "status": null
      },
      "otp_code": "472018",
      "pending_role_change": {
        "effective_date": null,
        "hr_case_id": null,
        "new_role_code": null
      },
      "phone_last_four": "3614",
      "role_code": "MANAGER",
      "software_licenses": []
    },
    "EMP072948": {
      "account_status": {
        "active_directory": {
          "lock_reason": null,
          "locked": false,
          "requires_in_person_reset": false
        },
        "email": {
          "lock_reason": null,
          "locked": false,
          "requires_in_person_reset": false
        },
        "erp": {
          "lock_reason": null,
          "locked": false,
          "requires_in_person_reset": false
        },
        "sso": {
          "lock_reason": null,
          "locked": false,
          "requires_in_person_reset": false
        },
        "vpn": {
          "lock_reason": null,
          "locked": false,
          "requires_in_person_reset": false
        }
      },
      "assigned_desk": "BLD3-FL2-D205",
      "assigned_parking": null,
      "building_code": "BLD3",
      "cost_center_code": "CC-1101",
      "date_of_birth": "1991-09-08",
      "department_code": "ENG",
      "direct_reports": [],
      "employee_id": "EMP072948",
      "employment_status": "off_boarding",
      "ergonomic_assessment": {
        "completed_date": null,
        "status": "not_completed"
      },
      "first_name": "Daniel",
      "floor_code": "FL2",
      "group_memberships": [
        {
          "added_date": "2021-02-01",
          "group_code": "GRP-ENGCORE",
          "group_name": "Engineering Core Access",
          "status": "active"
        },
        {
          "added_date": "2021-02-01",
          "group_code": "GRP-VPNEMP",
          "group_name": "Corporate VPN Users",
          "status": "active"
        }
      ],
      "hardware_entitlements": {
        "laptop_replacement": {
          "current_asset_tag": "AST-LPT-729480",
          "pending_request": false,
          "pending_request_id": null
        },
        "monitor_bundle": {
          "current_asset_tag": "AST-MON-729481",
          "pending_request": false,
          "pending_request_id": null
        }
      },
      "hire_date": "2021-02-01",
      "is_manager": false,
      "last_desk_assignment_date": "2026-02-01",
      "last_name": "Cho",
      "last_parking_assignment_date": null,
      "manager_auth_code": null,
      "manager_employee_id": "EMP031482",
      "offboarding_record": {
        "access_removed": false,
        "initiated_by": "HR",
        "initiated_date": "2026-08-27",
        "last_working_day": "2026-09-19",
        "removal_case_id": null,
        "removal_scope": null,
        "status": "confirmed"
      },
      "otp_code": "118204",
      "pending_role_change": {
        "effective_date": null,
        "hr_case_id": null,
        "new_role_code": null
      },
      "phone_last_four": "8421",
      "role_code": "SWE",
      "software_licenses": []
    }
  },
  "facilities": {
    "buildings": {
      "BLD3": {
        "name": "Downtown Engineering Center",
        "name_aliases": [
          "Downtown",
          "Engineering Center"
        ]
      }
    },
    "conference_rooms": {
      "BLD3-FL2-RM201": {
        "bookings": [],
        "building_code": "BLD3",
        "capacity": 8,
        "equipment": [
          "projector",
          "video_conferencing"
        ],
        "floor_code": "FL2"
      }
    },
    "desks": {
      "BLD3-FL2-D204": {
        "assigned_employee_id": "EMP031482",
        "building_code": "BLD3",
        "floor_code": "FL2",
        "near_window": true,
        "status": "assigned",
        "zone": "ENG-NORTH"
      },
      "BLD3-FL2-D205": {
        "assigned_employee_id": "EMP072948",
        "building_code": "BLD3",
        "floor_code": "FL2",
        "near_window": false,
        "status": "assigned",
        "zone": "ENG-NORTH"
      },
      "BLD3-FL3-D301": {
        "assigned_employee_id": "EMP000101",
        "building_code": "BLD3",
        "floor_code": "FL3",
        "near_window": true,
        "status": "assigned",
        "zone": "DIR-WEST"
      }
    },
    "parking": {
      "PZA-001": {
        "assigned_employee_id": "EMP000101",
        "covered": true,
        "level": "L1",
        "status": "assigned",
        "zone_code": "PZA"
      },
      "PZA-118": {
        "assigned_employee_id": "EMP031482",
        "covered": true,
        "level": "L2",
        "status": "assigned",
        "zone_code": "PZA"
      }
    },
    "zones": {
      "PZA": {
        "name": "Garage A",
        "name_aliases": [
          "A Garage",
          "Main Garage"
        ]
      }
    }
  },
  "field_dispatch_availability": {
    "BLD3": {
      "2026-09-02": {
        "afternoon": {
          "available": true,
          "technician_id": "T-118",
          "technician_name": "Sara Ng"
        },
        "morning": {
          "available": true,
          "technician_id": "T-104",
          "technician_name": "Luis Gomez"
        }
      }
    }
  },
  "interactions": {},
  "known_errors": {},
  "permission_templates": {},
  "requests": {},
  "security_cases": {},
  "session": {},
  "software_catalog": {
    "applications": {},
    "licenses": {}
  },
  "tickets": {},
  "troubleshooting_guides": {
    "hardware_malfunction": {
      "steps": [
        "Inspect the device for visible damage or loose cables.",
        "Power cycle the device fully.",
        "Reseat all connected cables and peripherals.",
        "Test with a known-good power source or peripheral."
      ]
    },
    "login_issue": {
      "steps": [
        "Confirm caps lock is off and retry sign-in.",
        "Try signing in through the web portal instead of the desktop app.",
        "Clear cached credentials and attempt sign-in again."
      ]
    },
    "network_connectivity": {
      "steps": [
        "Confirm Wi-Fi or ethernet is connected.",
        "Disconnect and reconnect to VPN.",
        "Restart the device network adapter.",
        "Open netdiag.company.com and run diagnostics."
      ]
    }
  },
  "waitlists": {}
}
